autodevice/__init__.py
autodevice/_autodevice.py
auto_device-0.0.0.dist-info/LICENSE
auto_device-0.0.0.dist-info/METADATA
auto_device-0.0.0.dist-info/WHEEL
auto_device-0.0.0.dist-info/top_level.txt
auto_device-0.0.0.dist-info/RECORD
