Metadata-Version: 2.1
Name: auto-device
Version: 0.0.0
Home-page: https://github.com/mvinyard/auto-device
Author: Michael E. Vinyard - Harvard University - Massachussetts General Hospital - Broad Institute of MIT and Harvard
Author-email: mvinyard@broadinstitute.org
License: MIT
Classifier: Development Status :: 2 - Pre-Alpha
Classifier: Programming Language :: Python :: 3.7
Classifier: Intended Audience :: Science/Research
Classifier: Topic :: Scientific/Engineering :: Bio-Informatics
Requires-Python: >3.7.0
License-File: LICENSE
Requires-Dist: torch (>=1.12.0)
